[
 {
   "Summary": "reconfigure LOCTA processing in Clearcore",
   "Issue key": "IDB-300",
   "Issue Type": "Task",
   "Status": "To Do",
   "Created": "2018-07-25",
   "Updated": "2018-07-25",
   "Last Viewed": "2018-07-25",
   "Resolved": "",
   "Custom field (Story Points)": 8
 },
 {
   "Summary": "Discover how the LOCTA processing in Clearcore should be set up",
   "Issue key": "IDB-299",
   "Issue Type": "Task",
   "Status": "Discovery",
   "Created": "2018-07-25",
   "Updated": "2018-07-27",
   "Last Viewed": "2018-07-27",
   "Resolved": "",
   "Custom field (Story Points)": 5
 },
 {
   "Summary": "Business Rule: Indicate excessive internal temperature for a prolonged period (unusually high temperatures (> 27°C))",
   "Issue key": "IDB-297",
   "Issue Type": "Task",
   "Status": "To Do",
   "Created": "2018-07-25",
   "Updated": "2018-07-25",
   "Last Viewed": "2018-07-25",
   "Resolved": "",
   "Custom field (Story Points)": 13
 },
 {
   "Summary": "Business Rule: Indicate early warning signs of fuel poverty (unusually low temperatures (< 18°C))",
   "Issue key": "IDB-284",
   "Issue Type": "New Feature",
   "Status": "To Do",
   "Created": "2018-07-18",
   "Updated": "2018-07-25",
   "Last Viewed": "2018-07-25",
   "Resolved": "",
   "Custom field (Story Points)": 3
 },
 {
   "Summary": "Identify the external temperature sensor to develop a relative temperature business rule",
   "Issue key": "IDB-277",
   "Issue Type": "Task",
   "Status": "Development",
   "Created": "2018-07-18",
   "Updated": "2018-07-27",
   "Last Viewed": "2018-07-25",
   "Resolved": "",
   "Custom field (Story Points)": 2
 },
 {
   "Summary": "Discover how to retrieve flat numbers via the Synetica API to identify properties",
   "Issue key": "IDB-276",
   "Issue Type": "Task",
   "Status": "To Do",
   "Created": "2018-07-18",
   "Updated": "2018-07-27",
   "Last Viewed": "2018-07-25",
   "Resolved": "",
   "Custom field (Story Points)": 3
 },
 {
   "Summary": "Access to the Boomi Atom and Molecule from the outside world",
   "Issue key": "IDB-274",
   "Issue Type": "Task",
   "Status": "Discovery",
   "Created": "2018-07-18",
   "Updated": "2018-07-27",
   "Last Viewed": "2018-07-25",
   "Resolved": "",
   "Custom field (Story Points)": 3
 },
 {
   "Summary": "SSO for the Boomi Platform",
   "Issue key": "IDB-272",
   "Issue Type": "Task",
   "Status": "Done",
   "Created": "2018-07-18",
   "Updated": "2018-07-26",
   "Last Viewed": "2018-07-27",
   "Resolved": "2018-07-26",
   "Custom field (Story Points)": 8
 },
 {
   "Summary": "PR002: Within Mendix, the API is not returning any context as to the error",
   "Issue key": "IDB-271",
   "Issue Type": "Improvement",
   "Status": "Done",
   "Created": "2018-07-17",
   "Updated": "2018-07-17",
   "Last Viewed": "2018-07-27",
   "Resolved": "2018-07-17",
   "Custom field (Story Points)": 2
 },
 {
   "Summary": "SP002: Create a Logger DB in LIVE",
   "Issue key": "IDB-268",
   "Issue Type": "Task",
   "Status": "Done",
   "Created": "2018-07-11",
   "Updated": "2018-07-20",
   "Last Viewed": "2018-07-27",
   "Resolved": "2018-07-13",
   "Custom field (Story Points)": 3
 },
 {
   "Summary": "CCR LIVE to include UPRN's",
   "Issue key": "IDB-267",
   "Issue Type": "Task",
   "Status": "Done",
   "Created": "2018-07-11",
   "Updated": "2018-07-20",
   "Last Viewed": "2018-07-27",
   "Resolved": "2018-07-17",
   "Custom field (Story Points)": 1
 },
 {
   "Summary": "PR002: Post Release",
   "Issue key": "IDB-266",
   "Issue Type": "Task",
   "Status": "Done",
   "Created": "2018-07-11",
   "Updated": "2018-07-23",
   "Last Viewed": "2018-07-27",
   "Resolved": "2018-07-23",
   "Custom field (Story Points)": 5
 },
 {
   "Summary": "PR002: CAB Approval - Update records",
   "Issue key": "IDB-265",
   "Issue Type": "Task",
   "Status": "Done",
   "Created": "2018-07-11",
   "Updated": "2018-07-23",
   "Last Viewed": "2018-07-27",
   "Resolved": "2018-07-23",
   "Custom field (Story Points)": 1
 },
 {
   "Summary": "PR002: CAB Approval - Release",
   "Issue key": "IDB-264",
   "Issue Type": "Task",
   "Status": "Done",
   "Created": "2018-07-11",
   "Updated": "2018-07-23",
   "Last Viewed": "2018-07-27",
   "Resolved": "2018-07-23",
   "Custom field (Story Points)": 1
 },
 {
   "Summary": "PR002: CAB Approval - Communications",
   "Issue key": "IDB-263",
   "Issue Type": "Task",
   "Status": "Done",
   "Created": "2018-07-11",
   "Updated": "2018-07-19",
   "Last Viewed": "2018-07-27",
   "Resolved": "2018-07-19",
   "Custom field (Story Points)": 2
 },
 {
   "Summary": "PR002: CAB Approval - Operational Setup",
   "Issue key": "IDB-262",
   "Issue Type": "Task",
   "Status": "Done",
   "Created": "2018-07-11",
   "Updated": "2018-07-23",
   "Last Viewed": "2018-07-27",
   "Resolved": "2018-07-23",
   "Custom field (Story Points)": 5
 },
 {
   "Summary": "PR002: CAB Approval - Testing",
   "Issue key": "IDB-261",
   "Issue Type": "Task",
   "Status": "Done",
   "Created": "2018-07-11",
   "Updated": "2018-07-18",
   "Last Viewed": "2018-07-27",
   "Resolved": "2018-07-18",
   "Custom field (Story Points)": 2
 },
 {
   "Summary": "PR002: CAB Approval - Readiness steps",
   "Issue key": "IDB-260",
   "Issue Type": "Task",
   "Status": "Done",
   "Created": "2018-07-11",
   "Updated": "2018-07-24",
   "Last Viewed": "2018-07-27",
   "Resolved": "2018-07-18",
   "Custom field (Story Points)": 2
 },
 {
   "Summary": "PR002: CAB Approval - Information Governance Review",
   "Issue key": "IDB-259",
   "Issue Type": "Task",
   "Status": "Done",
   "Created": "2018-07-11",
   "Updated": "2018-07-17",
   "Last Viewed": "2018-07-27",
   "Resolved": "2018-07-17",
   "Custom field (Story Points)": 3
 },
 {
   "Summary": "SP002: DPIA for the Logger",
   "Issue key": "IDB-258",
   "Issue Type": "Task",
   "Status": "Done",
   "Created": "2018-07-11",
   "Updated": "2018-07-13",
   "Last Viewed": "2018-07-27",
   "Resolved": "2018-07-13",
   "Custom field (Story Points)": 1
 },
 {
   "Summary": "Agree with IG for access to the Customer Index.",
   "Issue key": "IDB-256",
   "Issue Type": "Task",
   "Status": "Done",
   "Created": "2018-07-11",
   "Updated": "2018-07-20",
   "Last Viewed": "2018-07-27",
   "Resolved": "2018-07-20",
   "Custom field (Story Points)": 8
 },
 {
   "Summary": "Obtain DPIA for Council Tax and Benefits",
   "Issue key": "IDB-255",
   "Issue Type": "Task",
   "Status": "Done",
   "Created": "2018-07-11",
   "Updated": "2018-07-24",
   "Last Viewed": "2018-07-27",
   "Resolved": "2018-07-24",
   "Custom field (Story Points)": 5
 },
 {
   "Summary": "Obtain DPIA for Achieve",
   "Issue key": "IDB-254",
   "Issue Type": "Task",
   "Status": "Done",
   "Created": "2018-07-11",
   "Updated": "2018-07-24",
   "Last Viewed": "2018-07-27",
   "Resolved": "2018-07-24",
   "Custom field (Story Points)": 5
 },
 {
   "Summary": "SQL Demonstration of Customer Index ",
   "Issue key": "IDB-253",
   "Issue Type": "Task",
   "Status": "Done",
   "Created": "2018-07-11",
   "Updated": "2018-07-20",
   "Last Viewed": "2018-07-27",
   "Resolved": "2018-07-20",
   "Custom field (Story Points)": 1
 },
 {
   "Summary": "Connect to Synetica API on Boomi Atom using RESTLet",
   "Issue key": "IDB-252",
   "Issue Type": "Task",
   "Status": "Discovery",
   "Created": "2018-07-10",
   "Updated": "2018-07-27",
   "Last Viewed": "2018-07-25",
   "Resolved": "",
   "Custom field (Story Points)": 2
 },
 {
   "Summary": "PR002: Create a DPIA",
   "Issue key": "IDB-251",
   "Issue Type": "Task",
   "Status": "Done",
   "Created": "2018-07-10",
   "Updated": "2018-07-13",
   "Last Viewed": "2018-07-27",
   "Resolved": "2018-07-13",
   "Custom field (Story Points)": 1
 },
 {
   "Summary": "PR001: Create a DPIA",
   "Issue key": "IDB-250",
   "Issue Type": "Task",
   "Status": "Done",
   "Created": "2018-07-10",
   "Updated": "2018-07-13",
   "Last Viewed": "2018-07-27",
   "Resolved": "2018-07-13",
   "Custom field (Story Points)": 1
 },
 {
   "Summary": "Determine if viable to keep Achieve as a ClearCore data feed",
   "Issue key": "IDB-245",
   "Issue Type": "New Feature",
   "Status": "Deploy",
   "Created": "2018-07-05",
   "Updated": "2018-07-25",
   "Last Viewed": "2018-07-23",
   "Resolved": "",
   "Custom field (Story Points)": 5
 },
 {
   "Summary": "PR001: Re-schedule the process to run post ClearCore production ",
   "Issue key": "IDB-244",
   "Issue Type": "Task",
   "Status": "Done",
   "Created": "2018-06-29",
   "Updated": "2018-07-02",
   "Last Viewed": "2018-07-27",
   "Resolved": "2018-07-02",
   "Custom field (Story Points)": 0.5
 },
 {
   "Summary": "Re-schedule ClearCore to run inline with delivery of REC302 files",
   "Issue key": "IDB-243",
   "Issue Type": "Task",
   "Status": "Done",
   "Created": "2018-06-29",
   "Updated": "2018-07-03",
   "Last Viewed": "2018-07-27",
   "Resolved": "2018-07-03",
   "Custom field (Story Points)": 0.5
 },
 {
   "Summary": "PR002: Create a Mendix Front End for CCR Demo",
   "Issue key": "IDB-241",
   "Issue Type": "Task",
   "Status": "Done",
   "Created": "2018-06-27",
   "Updated": "2018-07-12",
   "Last Viewed": "2018-07-27",
   "Resolved": "2018-06-29",
   "Custom field (Story Points)": 5
 },
 {
   "Summary": "PR001: Devise a convincing front-end demonstration ",
   "Issue key": "IDB-240",
   "Issue Type": "Task",
   "Status": "Done",
   "Created": "2018-06-27",
   "Updated": "2018-07-19",
   "Last Viewed": "2018-07-27",
   "Resolved": "2018-07-19",
   "Custom field (Story Points)": 13
 },
 {
   "Summary": "Connect to Synetica API in Test",
   "Issue key": "IDB-235",
   "Issue Type": "Task",
   "Status": "Done",
   "Created": "2018-06-27",
   "Updated": "2018-06-29",
   "Last Viewed": "2018-07-27",
   "Resolved": "2018-06-28",
   "Custom field (Story Points)": 8
 },
 {
   "Summary": "Connect to iCasework API in Test",
   "Issue key": "IDB-230",
   "Issue Type": "Task",
   "Status": "Done",
   "Created": "2018-06-27",
   "Updated": "2018-07-26",
   "Last Viewed": "2018-07-23",
   "Resolved": "2018-07-26",
   "Custom field (Story Points)": 8
 },
 {
   "Summary": "API Publishing Procedure",
   "Issue key": "IDB-229",
   "Issue Type": "Task",
   "Status": "Done",
   "Created": "2018-06-25",
   "Updated": "2018-07-13",
   "Last Viewed": "2018-07-27",
   "Resolved": "2018-07-13",
   "Custom field (Story Points)": 2
 },
 {
   "Summary": "Amend stored procedure to return if a response for attempted duplicate insert",
   "Issue key": "IDB-228",
   "Issue Type": "Improvement",
   "Status": "Done",
   "Created": "2018-06-25",
   "Updated": "2018-07-06",
   "Last Viewed": "2018-07-27",
   "Resolved": "2018-07-06",
   "Custom field (Story Points)": 2
 },
 {
   "Summary": "PR001: CAB Approval - CAB [Standard Change]",
   "Issue key": "IDB-227",
   "Issue Type": "Task",
   "Status": "Done",
   "Created": "2018-06-25",
   "Updated": "2018-07-13",
   "Last Viewed": "2018-07-27",
   "Resolved": "2018-07-13",
   "Custom field (Story Points)": 1
 },
 {
   "Summary": "PR001: CAB Approval - TPAW [Standard Change]",
   "Issue key": "IDB-226",
   "Issue Type": "Task",
   "Status": "Done",
   "Created": "2018-06-25",
   "Updated": "2018-07-12",
   "Last Viewed": "2018-07-27",
   "Resolved": "2018-07-12",
   "Custom field (Story Points)": 3
 },
 {
   "Summary": "PR001: CAB Approval - IG [Standard Change]",
   "Issue key": "IDB-225",
   "Issue Type": "Task",
   "Status": "Done",
   "Created": "2018-06-25",
   "Updated": "2018-07-10",
   "Last Viewed": "2018-07-27",
   "Resolved": "2018-07-10",
   "Custom field (Story Points)": 13
 },
 {
   "Summary": "PR001: E-mail CCR address changes to business customer.",
   "Issue key": "IDB-221",
   "Issue Type": "New Feature",
   "Status": "Done",
   "Created": "2018-06-25",
   "Updated": "2018-07-03",
   "Last Viewed": "2018-07-27",
   "Resolved": "2018-07-03",
   "Custom field (Story Points)": 2
 },
 {
   "Summary": "PR002: Carryout code review for process",
   "Issue key": "IDB-218",
   "Issue Type": "Story",
   "Status": "Done",
   "Created": "2018-06-25",
   "Updated": "2018-07-12",
   "Last Viewed": "2018-07-18",
   "Resolved": "2018-07-06",
   "Custom field (Story Points)": 8
 },
 {
   "Summary": "SP002: Automatic method to restore process default log level after using exceptional log levels such as WARNING",
   "Issue key": "IDB-212",
   "Issue Type": "Improvement",
   "Status": "Done",
   "Created": "2018-06-22",
   "Updated": "2018-07-06",
   "Last Viewed": "2018-07-27",
   "Resolved": "2018-07-06",
   "Custom field (Story Points)": 2
 },
 {
   "Summary": "PR002: Carry out UAT of the CCR update address API to ensure it meets the needs of the business.",
   "Issue key": "IDB-206",
   "Issue Type": "Task",
   "Status": "Done",
   "Created": "2018-06-21",
   "Updated": "2018-07-17",
   "Last Viewed": "2018-07-27",
   "Resolved": "2018-07-17",
   "Custom field (Story Points)": 5
 },
 {
   "Summary": "PR001: Carry out UAT of the CCR update process to ensure it meets the needs of the business.",
   "Issue key": "IDB-205",
   "Issue Type": "Task",
   "Status": "Test",
   "Created": "2018-06-21",
   "Updated": "2018-07-25",
   "Last Viewed": "2018-07-27",
   "Resolved": "",
   "Custom field (Story Points)": 8
 },
 {
   "Summary": "Create documentation for ClearCore",
   "Issue key": "IDB-200",
   "Issue Type": "Task",
   "Status": "Done",
   "Created": "2018-06-19",
   "Updated": "2018-06-26",
   "Last Viewed": "2018-07-27",
   "Resolved": "2018-06-21",
   "Custom field (Story Points)": 5
 },
 {
   "Summary": "Create a Mendix front-end application ready to consume CCR Update Address API",
   "Issue key": "IDB-199",
   "Issue Type": "Task",
   "Status": "Done",
   "Created": "2018-06-15",
   "Updated": "2018-07-12",
   "Last Viewed": "2018-07-27",
   "Resolved": "2018-06-19",
   "Custom field (Story Points)": 3
 },
 {
   "Summary": "Connect to the Synetica API in the Boomi Platform to retrieve sensor data.",
   "Issue key": "IDB-188",
   "Issue Type": "Task",
   "Status": "Discovery",
   "Created": "2018-06-13",
   "Updated": "2018-07-27",
   "Last Viewed": "2018-07-25",
   "Resolved": "",
   "Custom field (Story Points)": 3
 },
 {
   "Summary": "Obtain DPIA for datasets connected to ClearCore",
   "Issue key": "IDB-181",
   "Issue Type": "Task",
   "Status": "Development",
   "Created": "2018-06-11",
   "Updated": "2018-07-25",
   "Last Viewed": "2018-07-27",
   "Resolved": "",
   "Custom field (Story Points)": 5
 },
 {
   "Summary": "Analysis: iWorld to ClearCore automation task",
   "Issue key": "IDB-178",
   "Issue Type": "Task",
   "Status": "Done",
   "Created": "2018-06-11",
   "Updated": "2018-06-26",
   "Last Viewed": "2018-07-27",
   "Resolved": "2018-06-26",
   "Custom field (Story Points)": 8
 },
 {
   "Summary": "iWorld API Understanding",
   "Issue key": "IDB-177",
   "Issue Type": "Task",
   "Status": "To Do",
   "Created": "2018-06-11",
   "Updated": "2018-06-22",
   "Last Viewed": "2018-07-27",
   "Resolved": "",
   "Custom field (Story Points)": 8
 },
 {
   "Summary": "As a JID, I need an Introduction to Mendix to understand how it consumes API's.",
   "Issue key": "IDB-175",
   "Issue Type": "Story",
   "Status": "Done",
   "Created": "2018-06-11",
   "Updated": "2018-06-26",
   "Last Viewed": "2018-07-27",
   "Resolved": "2018-06-22",
   "Custom field (Story Points)": 3
 },
 {
   "Summary": "As a developer, I need an API to allow my applications (e.g. Mendix) to publish address changes to CCR.",
   "Issue key": "IDB-173",
   "Issue Type": "Story",
   "Status": "Done",
   "Created": "2018-06-11",
   "Updated": "2018-07-12",
   "Last Viewed": "2018-07-27",
   "Resolved": "2018-06-22",
   "Custom field (Story Points)": 8
 },
 {
   "Summary": "PR001: External Code Review: Dell to Code Review",
   "Issue key": "IDB-172",
   "Issue Type": "Task",
   "Status": "Test",
   "Created": "2018-06-11",
   "Updated": "2018-07-18",
   "Last Viewed": "2018-07-27",
   "Resolved": "",
   "Custom field (Story Points)": 1
 },
 {
   "Summary": "Code Review: logging process [SP002]",
   "Issue key": "IDB-171",
   "Issue Type": "Task",
   "Status": "Done",
   "Created": "2018-06-08",
   "Updated": "2018-06-26",
   "Last Viewed": "2018-07-27",
   "Resolved": "2018-06-25",
   "Custom field (Story Points)": 8
 },
 {
   "Summary": "Logger training session and documentation",
   "Issue key": "IDB-169",
   "Issue Type": "Task",
   "Status": "Done",
   "Created": "2018-06-08",
   "Updated": "2018-06-26",
   "Last Viewed": "2018-07-27",
   "Resolved": "2018-06-25",
   "Custom field (Story Points)": 3
 },
 {
   "Summary": "Organise a ClearCore consultancy day to understand ClearCore",
   "Issue key": "IDB-167",
   "Issue Type": "Task",
   "Status": "Done",
   "Created": "2018-06-07",
   "Updated": "2018-06-26",
   "Last Viewed": "2018-07-27",
   "Resolved": "2018-06-15",
   "Custom field (Story Points)": 3
 },
 {
   "Summary": "Improve the logger process [SP002] to collect metrics",
   "Issue key": "IDB-165",
   "Issue Type": "Task",
   "Status": "Done",
   "Created": "2018-06-07",
   "Updated": "2018-06-26",
   "Last Viewed": "2018-07-27",
   "Resolved": "2018-06-18",
   "Custom field (Story Points)": 3
 },
 {
   "Summary": "Create a iPaaS template process to be used for all new processes",
   "Issue key": "IDB-164",
   "Issue Type": "Task",
   "Status": "Done",
   "Created": "2018-06-07",
   "Updated": "2018-06-26",
   "Last Viewed": "2018-07-27",
   "Resolved": "2018-06-18",
   "Custom field (Story Points)": 1
 },
 {
   "Summary": "Formulate a formal liaison process with RBTECH ",
   "Issue key": "IDB-163",
   "Issue Type": "Task",
   "Status": "Done",
   "Created": "2018-06-07",
   "Updated": "2018-06-21",
   "Last Viewed": "2018-07-27",
   "Resolved": "2018-06-21",
   "Custom field (Story Points)": 3
 },
 {
   "Summary": "As a data solutions team member, I need the REC302 data from iWorld to be automatically dropped daily into ClearCore for processing.",
   "Issue key": "IDB-162",
   "Issue Type": "Story",
   "Status": "Done",
   "Created": "2018-06-07",
   "Updated": "2018-06-29",
   "Last Viewed": "2018-07-27",
   "Resolved": "2018-06-29",
   "Custom field (Story Points)": 3
 },
 {
   "Summary": "Compile and order candidate data sources for Clearcore",
   "Issue key": "IDB-159",
   "Issue Type": "Task",
   "Status": "Done",
   "Created": "2018-06-07",
   "Updated": "2018-06-26",
   "Last Viewed": "2018-07-27",
   "Resolved": "2018-06-22",
   "Custom field (Story Points)": 8
 },
 {
   "Summary": "[Data Source Automation - template]",
   "Issue key": "IDB-147",
   "Issue Type": "Task",
   "Status": "To Do",
   "Created": "2018-05-24",
   "Updated": "2018-06-21",
   "Last Viewed": "2018-07-27",
   "Resolved": "",
   "Custom field (Story Points)": 10
 },
 {
   "Summary": "My Account ID Verification",
   "Issue key": "IDB-146",
   "Issue Type": "Task",
   "Status": "To Do",
   "Created": "2018-05-24",
   "Updated": "2018-06-21",
   "Last Viewed": "2018-07-27",
   "Resolved": "",
   "Custom field (Story Points)": 8
 },
 {
   "Summary": "Investigate a number of different and unrelated items",
   "Issue key": "IDB-144",
   "Issue Type": "Epic",
   "Status": "To Do",
   "Created": "2018-05-24",
   "Updated": "2018-06-21",
   "Last Viewed": "2018-07-27",
   "Resolved": "",
   "Custom field (Story Points)": 10
 },
 {
   "Summary": "Processing Advice for Anonymising ",
   "Issue key": "IDB-143",
   "Issue Type": "Task",
   "Status": "Done",
   "Created": "2018-05-24",
   "Updated": "2018-06-06",
   "Last Viewed": "2018-07-27",
   "Resolved": "2018-06-06",
   "Custom field (Story Points)": 2
 },
 {
   "Summary": "Boomi Naming Convention",
   "Issue key": "IDB-141",
   "Issue Type": "Improvement",
   "Status": "Done",
   "Created": "2018-05-24",
   "Updated": "2018-06-22",
   "Last Viewed": "2018-07-27",
   "Resolved": "2018-05-31",
   "Custom field (Story Points)": 2
 },
 {
   "Summary": "Formalise the 'Commit' Process for Boomi Processes",
   "Issue key": "IDB-140",
   "Issue Type": "Improvement",
   "Status": "Done",
   "Created": "2018-05-24",
   "Updated": "2018-06-22",
   "Last Viewed": "2018-07-27",
   "Resolved": "2018-06-08",
   "Custom field (Story Points)": 2
 },
 {
   "Summary": "House Keeping on Boomi Platform",
   "Issue key": "IDB-139",
   "Issue Type": "Improvement",
   "Status": "Done",
   "Created": "2018-05-24",
   "Updated": "2018-06-08",
   "Last Viewed": "2018-07-27",
   "Resolved": "2018-06-08",
   "Custom field (Story Points)": 1
 },
 {
   "Summary": "Code Review Process",
   "Issue key": "IDB-138",
   "Issue Type": "Improvement",
   "Status": "Done",
   "Created": "2018-05-24",
   "Updated": "2018-06-22",
   "Last Viewed": "2018-07-27",
   "Resolved": "2018-05-30",
   "Custom field (Story Points)": 5
 },
 {
   "Summary": "Define and run functional test cases",
   "Issue key": "IDB-137",
   "Issue Type": "Improvement",
   "Status": "Done",
   "Created": "2018-05-24",
   "Updated": "2018-06-06",
   "Last Viewed": "2018-07-27",
   "Resolved": "2018-06-06",
   "Custom field (Story Points)": 5
 },
 {
   "Summary": "Permanent Boomi DIR for INPUT, OUT and LOGGING ",
   "Issue key": "IDB-134",
   "Issue Type": "Improvement",
   "Status": "Done",
   "Created": "2018-05-24",
   "Updated": "2018-05-31",
   "Last Viewed": "2018-07-27",
   "Resolved": "2018-05-31",
   "Custom field (Story Points)": 1
 },
 {
   "Summary": "Investigation of Atmosphere function for identifying duplicated records",
   "Issue key": "IDB-132",
   "Issue Type": "Improvement",
   "Status": "Done",
   "Created": "2018-05-24",
   "Updated": "2018-05-30",
   "Last Viewed": "2018-07-27",
   "Resolved": "2018-05-30",
   "Custom field (Story Points)": 2
 },
 {
   "Summary": "Confirm the Usability of Test Data",
   "Issue key": "IDB-131",
   "Issue Type": "Task",
   "Status": "Done",
   "Created": "2018-05-24",
   "Updated": "2018-06-07",
   "Last Viewed": "2018-07-27",
   "Resolved": "2018-06-07",
   "Custom field (Story Points)": 8
 },
 {
   "Summary": "Test / Production ClearCore Mismatch",
   "Issue key": "IDB-130",
   "Issue Type": "Impediment",
   "Status": "Done",
   "Created": "2018-05-24",
   "Updated": "2018-05-31",
   "Last Viewed": "2018-07-27",
   "Resolved": "2018-05-31",
   "Custom field (Story Points)": 0
 },
 {
   "Summary": "Rebuild Test ClearCore Environment",
   "Issue key": "IDB-129",
   "Issue Type": "Impediment",
   "Status": "Done",
   "Created": "2018-05-24",
   "Updated": "2018-06-04",
   "Last Viewed": "2018-07-27",
   "Resolved": "2018-05-31",
   "Custom field (Story Points)": 0
 },
 {
   "Summary": "Code Cleanup",
   "Issue key": "IDB-127",
   "Issue Type": "Improvement",
   "Status": "Done",
   "Created": "2018-05-24",
   "Updated": "2018-06-07",
   "Last Viewed": "2018-07-27",
   "Resolved": "2018-06-07",
   "Custom field (Story Points)": 3
 },
 {
   "Summary": "Integration Connection Test",
   "Issue key": "IDB-125",
   "Issue Type": "Task",
   "Status": "Done",
   "Created": "2018-05-24",
   "Updated": "2018-06-07",
   "Last Viewed": "2018-07-27",
   "Resolved": "2018-06-07",
   "Custom field (Story Points)": 8
 },
 {
   "Summary": "ClearCore Output Process Change",
   "Issue key": "IDB-123",
   "Issue Type": "New Feature",
   "Status": "Done",
   "Created": "2018-05-22",
   "Updated": "2018-06-05",
   "Last Viewed": "2018-07-27",
   "Resolved": "2018-06-05",
   "Custom field (Story Points)": 0.5
 },
 {
   "Summary": "ClearCore Output File Location - DEV",
   "Issue key": "IDB-122",
   "Issue Type": "New Feature",
   "Status": "Done",
   "Created": "2018-05-22",
   "Updated": "2018-05-31",
   "Last Viewed": "2018-07-27",
   "Resolved": "2018-05-31",
   "Custom field (Story Points)": 2
 },
 {
   "Summary": "Error Cases",
   "Issue key": "IDB-121",
   "Issue Type": "New Feature",
   "Status": "Done",
   "Created": "2018-05-22",
   "Updated": "2018-06-26",
   "Last Viewed": "2018-07-27",
   "Resolved": "2018-06-07",
   "Custom field (Story Points)": 8
 },
 {
   "Summary": "Validation: Feed CCR Address changes into ClearCore",
   "Issue key": "IDB-119",
   "Issue Type": "Task",
   "Status": "Done",
   "Created": "2018-05-18",
   "Updated": "2018-06-25",
   "Last Viewed": "2018-07-27",
   "Resolved": "2018-06-25",
   "Custom field (Story Points)": 1
 },
 {
   "Summary": "Match the expected address with the actual address changes in the DELTA",
   "Issue key": "IDB-118",
   "Issue Type": "Task",
   "Status": "Done",
   "Created": "2018-05-18",
   "Updated": "2018-06-26",
   "Last Viewed": "2018-07-27",
   "Resolved": "2018-06-22",
   "Custom field (Story Points)": 0.5
 },
 {
   "Summary": "Keep a history of address changes in CCR",
   "Issue key": "IDB-117",
   "Issue Type": "Task",
   "Status": "Done",
   "Created": "2018-05-18",
   "Updated": "2018-05-23",
   "Last Viewed": "2018-07-27",
   "Resolved": "2018-05-23",
   "Custom field (Story Points)": 0
 },
 {
   "Summary": "Call the CCR 'update address' stored procedure",
   "Issue key": "IDB-116",
   "Issue Type": "Task",
   "Status": "Done",
   "Created": "2018-05-18",
   "Updated": "2018-05-23",
   "Last Viewed": "2018-07-27",
   "Resolved": "2018-05-23",
   "Custom field (Story Points)": 1
 },
 {
   "Summary": "Test and refine the Boomi Process",
   "Issue key": "IDB-115",
   "Issue Type": "Task",
   "Status": "Done",
   "Created": "2018-05-18",
   "Updated": "2018-06-26",
   "Last Viewed": "2018-07-27",
   "Resolved": "2018-06-07",
   "Custom field (Story Points)": 13
 },
 {
   "Summary": "Build the Boomi Process.",
   "Issue key": "IDB-114",
   "Issue Type": "Task",
   "Status": "Done",
   "Created": "2018-05-18",
   "Updated": "2018-05-23",
   "Last Viewed": "2018-07-27",
   "Resolved": "2018-05-23",
   "Custom field (Story Points)": 8
 },
 {
   "Summary": "Breakdown and plan for Boomi process.",
   "Issue key": "IDB-113",
   "Issue Type": "Task",
   "Status": "Done",
   "Created": "2018-05-18",
   "Updated": "2018-05-21",
   "Last Viewed": "2018-07-27",
   "Resolved": "2018-05-21",
   "Custom field (Story Points)": 5
 },
 {
   "Summary": "Formalise address format in CCR database - UPRN etc. Add UPRN's to CCR address database match and insert.",
   "Issue key": "IDB-111",
   "Issue Type": "Task",
   "Status": "Done",
   "Created": "2018-05-18",
   "Updated": "2018-05-18",
   "Last Viewed": "2018-07-27",
   "Resolved": "2018-05-18",
   "Custom field (Story Points)": 5
 },
 {
   "Summary": "Analyse exsititing CCR client address quality in TEST. Match address with UPRN to LLPG.",
   "Issue key": "IDB-110",
   "Issue Type": "Task",
   "Status": "Done",
   "Created": "2018-05-18",
   "Updated": "2018-05-18",
   "Last Viewed": "2018-07-27",
   "Resolved": "2018-05-18",
   "Custom field (Story Points)": 5
 },
 {
   "Summary": "Create test data.",
   "Issue key": "IDB-106",
   "Issue Type": "Task",
   "Status": "Done",
   "Created": "2018-05-18",
   "Updated": "2018-05-23",
   "Last Viewed": "2018-07-27",
   "Resolved": "2018-05-23",
   "Custom field (Story Points)": 8
 },
 {
   "Summary": "Gather and collate baseline metrics",
   "Issue key": "IDB-105",
   "Issue Type": "New Feature",
   "Status": "Done",
   "Created": "2018-05-18",
   "Updated": "2018-06-26",
   "Last Viewed": "2018-07-27",
   "Resolved": "2018-06-19",
   "Custom field (Story Points)": 8
 },
 {
   "Summary": "Understand ClearCore 'Poll for change' report.",
   "Issue key": "IDB-104",
   "Issue Type": "Task",
   "Status": "Done",
   "Created": "2018-05-18",
   "Updated": "2018-05-21",
   "Last Viewed": "2018-07-27",
   "Resolved": "2018-05-21",
   "Custom field (Story Points)": 2
 },
 {
   "Summary": "Pickup changes from ClearCore - consume ClearCore CSV or SQL.",
   "Issue key": "IDB-103",
   "Issue Type": "Task",
   "Status": "Done",
   "Created": "2018-05-18",
   "Updated": "2018-05-22",
   "Last Viewed": "2018-07-27",
   "Resolved": "2018-05-22",
   "Custom field (Story Points)": 2
 },
 {
   "Summary": "Understand business processes for CCR",
   "Issue key": "IDB-102",
   "Issue Type": "Task",
   "Status": "Done",
   "Created": "2018-05-17",
   "Updated": "2018-05-23",
   "Last Viewed": "2018-07-27",
   "Resolved": "2018-05-23",
   "Custom field (Story Points)": 2
 },
 {
   "Summary": "Architectural understanding of systems (ClearCore, CCR & Mendix)",
   "Issue key": "IDB-101",
   "Issue Type": "Task",
   "Status": "Done",
   "Created": "2018-05-17",
   "Updated": "2018-05-21",
   "Last Viewed": "2018-07-27",
   "Resolved": "2018-05-21",
   "Custom field (Story Points)": 2
 }
]